ansible_extra_tools/__init__.py
ansible_extra_tools/role.py
ansible_extra_tools-0.2.0.dist-info/licenses/LICENSE
ansible_extra_tools-0.2.0.dist-info/METADATA
ansible_extra_tools-0.2.0.dist-info/WHEEL
ansible_extra_tools-0.2.0.dist-info/entry_points.txt
ansible_extra_tools-0.2.0.dist-info/top_level.txt
ansible_extra_tools-0.2.0.dist-info/RECORD
