Metadata-Version: 2.4
Name: ansible-extra-tools
Version: 0.2.0
Summary: Extra tools for Ansible
Author: Dan Griffin
License:                     GNU GENERAL PUBLIC LICENSE
Project-URL: homepage, https://github.com/dwgriffin/ansible-extra-tools
Project-URL: repository, https://github.com/dwgriffin/ansible-extra-tools
Keywords: ansible
Classifier: Intended Audience :: System Administrators
Classifier: License :: OSI Approved :: GNU General Public License v3 or later (GPLv3+)
Classifier: Programming Language :: Python :: 3
Classifier: Programming Language :: Python :: 3.9
Classifier: Programming Language :: Python :: 3.10
Classifier: Programming Language :: Python :: 3.11
Classifier: Programming Language :: Python :: 3.12
Classifier: Programming Language :: Python :: 3.13
Classifier: Programming Language :: Python :: 3.14
Classifier: Programming Language :: Python :: 3 :: Only
Classifier: Topic :: System :: Systems Administration
Classifier: Topic :: Utilities
Requires-Python: >=3.9
License-File: LICENSE
Requires-Dist: ansible-core>=2.15
Dynamic: license-file
